iris_coon/__init__.py
iris_coon/cli.py
iris_coon/core.py
iris_coon-0.6.1.dist-info/METADATA
iris_coon-0.6.1.dist-info/WHEEL
iris_coon-0.6.1.dist-info/entry_points.txt
iris_coon-0.6.1.dist-info/RECORD
