Metadata-Version: 2.1
Name: iris-coon
Version: 0.6.1
Summary: IRISリポジトリをクローンし、.githubフォルダをコピーするパッケージ
Author: Maki
Author-email: sunwood.ai.labs@gmail.com
Requires-Python: >=3.12,<4.0
Classifier: Programming Language :: Python :: 3
Classifier: Programming Language :: Python :: 3.12
Requires-Dist: art (>=6.2,<7.0)
Requires-Dist: click (>=8.1.7,<9.0.0)
Requires-Dist: gitpython (>=3.1.43,<4.0.0)
Requires-Dist: loguru (>=0.7.2,<0.8.0)
Requires-Dist: rich (>=13.7.1,<14.0.0)
